{
  "collectionName": "components_ingredients_beverage_ingredients",
  "info": {
    "displayName": "Beverage Ingredients",
    "description": ""
  },
  "options": {},
  "attributes": {
    "Quantity": {
      "type": "decimal"
    },
    "Units": {
      "type": "enumeration",
      "enum": [
        "oz",
        "ml",
        "l",
        "g",
        "tsp",
        "tbs",
        "drop",
        "drops",
        "slices",
        "swatch",
        "leaves",
        "wedges",
        "scoop",
        "hs",
        "ea"
      ],
      "default": "oz"
    },
    "Item": {
      "type": "string"
    }
  }
}
